d4/__init__.py
d4/_cmd.py
d4/_d4.py
d4/_exception.py
d4/_interactions.py
d4/_models.py
d4/_otobot.py
d4/_requests.py
d4/_utils.py
d4/temp.py
d4/temp2.py
d4_py-0.0.0.10a4.dist-info/METADATA
d4_py-0.0.0.10a4.dist-info/WHEEL
d4_py-0.0.0.10a4.dist-info/top_level.txt
d4_py-0.0.0.10a4.dist-info/RECORD
