Metadata-Version: 2.1
Name: d4-py
Version: 0.0.0.10a4
Summary: d4.py pre-alpha v0.0.0.10a
Home-page: https://github.com/namuKR/d4.py
Author: ast.08
Author-email: <ast.08e@gmail.com>
License: UNKNOWN
Platform: UNKNOWN
Classifier: Programming Language :: Python :: 3
Classifier: License :: OSI Approved :: Apache Software License
Requires-Python: >=3.6
Requires-Dist: requests
Requires-Dist: asyncio
Requires-Dist: aiohttp
